{
  "version": 0,
  "updated_at": "2025-02-07T12:00:00Z",
  "intro": {
    "name": "Md. Yeasin Sheikh",
    "title": "Software Developer | Flutter specialist",
    "short_title": "Software Developer | Flutter",
    "description": "A limited lifespan who loves to solve problems and create values."
  },

  "connects": [
    {
      "name": "github",
      "logo": "https://raw.githubusercontent.com/yeasin50/yeasin50/refs/heads/master/assets/logo/github.png",
      "url": "https://github.com/yeasin50"
    },
    {
      "name": "stackOverflow",
      "logo": "https://raw.githubusercontent.com/yeasin50/yeasin50/refs/heads/master/assets/logo/stackoverflow.png",
      "url": "https://stackoverflow.com/users/10157127/md-yeasin-sheikh"
    },
    {
      "name": "linkedin",
      "logo": "https://raw.githubusercontent.com/yeasin50/yeasin50/refs/heads/master/assets/logo/Linkedin.png",
      "url": "https://www.linkedin.com/in/mdyeasinsheikh/"
    },
    {
      "name": "youtube",
      "logo": "https://raw.githubusercontent.com/yeasin50/yeasin50/refs/heads/master/assets/logo/yt.png",
      "url": "https://www.youtube.com/@FlutterforMe"
    }
  ],

  "experience": [
    {
      "title": "Software Engineer",
      "organization": {
        "name": "Upwork"
      },
      "start": "2021-07-01T00:00:00Z",
      "end": null,
      "description": "Freelance hybrid developer with extensive experience in bringing creative ideas to life. Led multiple projects, including DataHub for Daffodil Health Department, and worked on a variety of Flutter-based applications."
    },
    {
      "title": "Flutter Developer",
      "organization": {
        "name": "Tincleo"
      },
      "start": "2023-12-01T00:00:00Z",
      "end": "2024-11-30T00:00:00Z",
      "description": "Flutter development on various projects."
    },
    {
      "title": "Flutter Developer",
      "organization": {
        "name": "Oxford International School"
      },
      "start": "2024-08-01T00:00:00Z",
      "end": "2024-09-30T00:00:00Z",
      "description": "Built Moneybag Flutter package, a leading payment gateway in Bangladesh."
    },
    {
      "title": "Flutter Developer Intern",
      "organization": {
        "name": "OSGRIP Technologies"
      },
      "start": "2021-06-01T00:00:00Z",
      "end": "2021-09-30T00:00:00Z",
      "description": "Contributed to Travellers App, improving UI and integrating API data."
    },
    {
      "title": "Mobile Application Developer Intern",
      "organization": {
        "name": "The Sparks Foundation"
      },
      "start": "2021-03-01T00:00:00Z",
      "end": "2021-05-31T00:00:00Z",
      "description": "Built a basic banking system focusing on interactive UI."
    }
  ],
  "education": [
    {
      "school": {
        "name": "Daffodil International University"
      },
      "degree": "Bachelor",
      "field": "Computer Science and Engineering",
      "start": "2018-01-01T00:00:00Z",
      "end": "2023-09-01T00:00:00Z",
      "grade": "3.67 out of 4.0",
      "description": "Not that efficient for my limited lifespan",
      "images": []
    }
  ],
  "certificate": [
    {
      "name": "FlutterDevcamp State Management Special",
      "organization": {
        "name": "GDG London"
      },
      "credential_url": null,
      "image_url": null,
      "issue_date": "2023-09-01T00:00:00Z",
      "expiration_date": null
    },
    {
      "name": "Engineering: Undergraduate & Masters Asia Virtual Experience Program",
      "organization": {
        "name": "Microsoft"
      },
      "credential_url": null,
      "image_url": null,
      "issue_date": "2021-06-01T00:00:00Z",
      "expiration_date": null
    },
    {
      "name": "Foundations of User Experience (UX) Design",
      "organization": {
        "name": "Google"
      },
      "credential_url": null,
      "image_url": null,
      "issue_date": "2021-05-01T00:00:00Z",
      "expiration_date": null
    }
  ],
  "projects": [
    {
      "id": "1",
      "title": "FamTree",
      "description": "Create Family tree, share with others, collaborate and chat with family members.",
      "category": "Mobile Application",
      "roll": "Flutter Developer",
      "created_at": "2023-11-01T00:00:00Z",
      "thumbnail": "",
      "media": [],
      "tasks": [
        "Developed the main UI",
        "Implemented real-time chat functionality",
        "Ensured seamless family tree collaboration"
      ]
    },
    {
      "id": "2",
      "title": "Personal Formula Assistant",
      "description": "Helps students access mathematical formulas offline and search by title.",
      "category": "Mobile Application",
      "roll": "Flutter Developer",
      "created_at": "2023-06-01T00:00:00Z",
      "thumbnail": "",
      "media": [],
      "tasks": [
        "Designed UI for offline access",
        "Implemented search functionality"
      ]
    },
    {
      "id": "3",
      "title": "Flutter 2D Space Craft Game",
      "description": "A fun 2D game built with Flutter using CustomPaint and custom logic.",
      "category": "Game Development",
      "roll": "Game Developer",
      "created_at": "2021-01-01T00:00:00Z",
      "thumbnail": "",
      "media": [],
      "tasks": [
        "Developed game mechanics",
        "Created custom UI without asset images"
      ]
    },
    {
      "id": "4",
      "title": "Lisa Fischer Portfolio Clone",
      "description": "Web project using Flutter Navigator 2.0 to clone Lisa Fischer’s portfolio.",
      "category": "Web Development",
      "roll": "Flutter Developer",
      "created_at": "2021-08-01T00:00:00Z",
      "thumbnail": "",
      "media": [],
      "tasks": [
        "Implemented navigation using Navigator 2.0",
        "Designed UI to match original portfolio"
      ]
    }
  ]
}
